Workbook

Sheet Facility
A1: FacilityName | B1: RespondentName | C1: JobTitle | D1: FacilityLevel | E1: CountySubcounty | F1: CostingStart | G1: CostingEnd | H1: CatchmentPop | I1: AnnualOPD | J1: AnnualTBScreened | K1: TB Positive Cases | L1: AnnualPPTB_Eligible (TB ruled out) | M1: AnnualCRDPatients (ssen for CDR diagnosis) | N1: AnnualCXR | O1: AnnualSpirometry | P1: CRDInTBClinic | Q1: TotalFacilityM2 | R1: FormFillMinutes | S1: Flag
A2: Rhodes Chest Clinic | B2: Patrick Maingi | C2: Senior chest clinician | D2: Level 2 | E2: Nairobi, Starehe | F2: 45839 | G2: 46203 | H2: 7000 | I2: 6000 | J2: 3671 | K2: 418 | L2: 929 | M2: 255 | N2: 4000 | O2: 563 | P2: Yes | Q2: 10000 | R2: 90 | S2: Total floor parsed from "100by 100"=10,000 m2 (may be feet); CXR 4000 > TB screened 2000 and spirometry 1500 > CRD patients 255 - volumes inconsistent
A3: Riruta Health Centre | B3: Alice Ndwiga | C3: Facility Manager | D3: Level 3 | E3: Nairobi, Dagoretti North | F3: 45839 | G3: 46203 | H3: 72038 | I3: 14741 | J3: 11930 | K3: 132 | L3: 1256 | M3: 204 | N3: 67 | O3: 320 | P3: Yes | Q3: 800 | R3: 65 | S3: PPTB-eligible 262 < CRD patients 1545 - funnel inconsistent; verify question interpretation
A4: Karen Health Centre | B4: Angeline Mang'ati | C4: Facility in charge | D4: Level 3 | E4: Nairobi, Langata | F4: 45839 | G4: 46203 | H4: 28587 | I4: 11586 | J4: 752 | K4: 42 | L4: 408 | M4: 366 | N4: 205 | O4: 127 | P4: Yes | Q4: 800 | R4: 45 | S4: Start date fixed from 2025-01-07 (day/month swap); end date parsed from text; total floor "4 X 3"=12 m2 invalid -> imputed 800 m2 (peer Level 3 proxy)

Sheet Staff
A1: FacilityName | B1: Cadre | C1: WhoHandles | D1: StaffCount | E1: MonthlySalaryKES | F1: MonthlyAllowancesKES | G1: HoursPerMonth | H1: MinutesPerPatient | I1: CRDTimePct | J1: AnnualCRDStaffCostKES | K1: Flag
A2: Rhodes Chest Clinic | B2: Registration | C2: Records Officer | E2: 47000 | F2: 0 | G2: 160 | H2: 30 | I2: 0.4 | J2: =(E2+F2)*12*I2 -> 225600
A3: Rhodes Chest Clinic | B3: Triage | C3: Community Health Volunteer, Nurse | D3: 3 | E3: 115000 | F3: 0 | G3: 160 | H3: 30 | I3: 0.4 | J3: =(E3+F3)*12*I3 -> 552000 | K3: Salary summed from "triage nurse-100,000,chv-15000"
A4: Rhodes Chest Clinic | B4: Consultation | C4: Clinical Officer, Respiratory Clinician | D4: 2 | E4: 120000 | F4: 0 | G4: 160 | H4: 25 | I4: 0.3 | J4: =(E4+F4)*12*I4 -> 432000 | K4: Pct entered as 30 -> 30%
A5: Rhodes Chest Clinic | B5: Laboratory | C5: Laboratory Technologist | D5: 2 | E5: 100000 | F5: 0 | G5: 160 | H5: 20 | I5: 0.2 | J5: =(E5+F5)*12*I5 -> 240000 | K5: Pct entered as 20 -> 20%
A6: Rhodes Chest Clinic | B6: Radiology | C6: Radiographer | D6: 2 | E6: 110000 | F6: 0 | G6: 160 | H6: 10 | I6: 0.1 | J6: =(E6+F6)*12*I6 -> 132000
A7: Rhodes Chest Clinic | B7: Spirometry | C7: Nurse, Clinical Officer | D7: 3 | E7: 110000 | F7: 0 | G7: 100 | H7: 30 | I7: 0.3 | J7: =(E7+F7)*12*I7 -> 396000
A8: Rhodes Chest Clinic | B8: Counselling | C8: Counsellor | D8: 1 | E8: 40000 | F8: 0 | G8: 160 | H8: 30 | I8: 0.3 | J8: =(E8+F8)*12*I8 -> 144000
A9: Riruta Health Centre | B9: Registration | C9: Records Officer | E9: 50000 | F9: 0 | G9: 160 | H9: 4 | I9: 0.1048 | J9: =(E9+F9)*12*I9 -> 62880 | K9: Minutes from "3-5 mins" -> 4; allowances blank -> 0
A10: Riruta Health Centre | B10: Triage | C10: Nurse | D10: 3 | E10: 55000 | F10: 0 | G10: 160 | H10: 6.5 | I10: 0.18 | J10: =(E10+F10)*12*I10 -> 118800 | K10: Minutes from "5-8 mins" -> 6.5
A11: Riruta Health Centre | B11: Consultation | C11: Clinical Officer | D11: 2 | E11: 55000 | F11: 0 | G11: 160 | H11: 15 | I11: 0.5 | J11: =(E11+F11)*12*I11 -> 330000 | K11: Minutes from "10-20 mins" -> 15
A12: Riruta Health Centre | B12: Laboratory | C12: Nurse | D12: 3 | E12: 50000 | F12: 0 | G12: 160 | H12: 45 | I12: 0.3 | J12: =(E12+F12)*12*I12 -> 180000 | K12: Count from "0-6" -> 3 (midpoint); minutes from "30min-1hour" -> 45
A13: Riruta Health Centre | B13: Radiology | C13: Radiographer | D13: 2 | E13: 50000 | F13: 0 | G13: 160 | H13: 12.5 | I13: 0.18 | J13: =(E13+F13)*12*I13 -> 108000 | K13: Minutes from "10-15mins" -> 12.5; NOTE facility reports no radiology service and 0 X-rays
A14: Riruta Health Centre | B14: Spirometry | C14: Clinical Officer | D14: 1 | E14: 50000 | F14: 0 | G14: 160 | H14: 30 | I14: 0.8 | J14: =(E14+F14)*12*I14 -> 480000 | K14: CRD share 80% is unusually high - verify
A15: Riruta Health Centre | B15: Counselling | C15: Clinical Officer | D15: 1 | E15: 50000 | F15: 0 | G15: 160 | H15: 25 | I15: 0.14 | J15: =(E15+F15)*12*I15 -> 84000 | K15: Allowances "N/a" -> 0; minutes from "20-30mins" -> 25
A16: Karen Health Centre | B16: Registration | C16: Records Officer | E16: 75000 | F16: 0 | G16: 160 | H16: 5 | I16: 0.2 | J16: =(E16+F16)*12*I16 -> 180000
A17: Karen Health Centre | B17: Triage | C17: Community Health Volunteer, Nurse | D17: 2 | E17: 105000 | F17: 0 | G17: 160 | H17: 6 | I17: 0.25 | J17: =(E17+F17)*12*I17 -> 315000 | K17: Salary summed from "NURSE- 90,000, CHV- 15,000"; minutes cell held date 2026-05-07 = "5-7" entered -> 6
A18: Karen Health Centre | B18: Consultation | C18: Nurse, Clinical Officer | D18: 3 | E18: 180000 | F18: 0 | G18: 160 | H18: 10 | I18: 0.25 | J18: =(E18+F18)*12*I18 -> 540000 | K18: Salary summed from "Nurse- 90,000, C.O- 90,000"
A19: Karen Health Centre | B19: Laboratory | C19: Laboratory Technologist | D19: 3 | E19: 90000 | F19: 0 | G19: 160 | H19: 5 | I19: 0.2 | J19: =(E19+F19)*12*I19 -> 216000 | K19: Pct entered as 20 -> 20%
A20: Karen Health Centre | B20: Radiology | C20: Radiographer | D20: 1 | E20: 90000 | F20: 0 | G20: 80 | H20: 20 | I20: 0.25 | J20: =(E20+F20)*12*I20 -> 270000
A21: Karen Health Centre | B21: Spirometry | C21: Radiographer | D21: 1 | E21: 90000 | F21: 0 | G21: 60 | H21: 20 | I21: 0.3 | J21: =(E21+F21)*12*I21 -> 324000 | K21: Pct entered as 30 -> 30%
A22: Karen Health Centre | B22: Counselling | C22: Nurse, Clinical Officer | D22: 2 | E22: 90000 | F22: 0 | G22: 160 | H22: 5 | I22: 0.15 | J22: =(E22+F22)*12*I22 -> 162000

Sheet Equipment
A1: FacilityName | B1: Item | C1: Stage | D1: Quantity | E1: ReplacementValueKES | F1: AnnualMaintenanceKES | G1: CRDUsePct | H1: UsefulLifeYears | I1: AnnualizedValuePerUnitKES | J1: AllocatedAnnualCostKES | K1: Flag
A2: Rhodes Chest Clinic | B2: Spirometer | C2: Spirometry | D2: 1 | E2: 250000 | F2: 100000 | G2: 0.5 | H2: 5 | I2: =IFERROR(E2*0.03/(1-POWER(1.03,-H2)),0) -> 54588.643 | J2: =(I2*D2+F2)*G2 -> 77294.321
A3: Rhodes Chest Clinic | B3: Calibration syringe | C3: Spirometry | D3: 0 | E3: 0 | F3: 0 | G3: 0 | H3: 5 | I3: =IFERROR(E3*0.03/(1-POWER(1.03,-H3)),0) -> 0 | J3: =(I3*D3+F3)*G3 -> 0 | K3: Not owned / all zeros
A4: Rhodes Chest Clinic | B4: Laptop/tablet for spirometry | C4: Spirometry | D4: 2 | E4: 60000 | F4: 10000 | G4: 0.7 | H4: 4 | I4: =IFERROR(E4*0.03/(1-POWER(1.03,-H4)),0) -> 16141.623 | J4: =(I4*D4+F4)*G4 -> 29598.272
A5: Rhodes Chest Clinic | B5: Pulse oximeter | C5: Triage | D5: 4 | E5: 12000 | F5: 4000 | G5: 0.5 | H5: 3 | I5: =IFERROR(E5*0.03/(1-POWER(1.03,-H5)),0) -> 4242.3644 | J5: =(I5*D5+F5)*G5 -> 10484.729
A6: Rhodes Chest Clinic | B6: Chest X-ray machine | C6: Radiology | D6: 1 | E6: 6000000 | F6: 200000 | G6: 0.4 | H6: 10 | I6: =IFERROR(E6*0.03/(1-POWER(1.03,-H6)),0) -> 703383.04 | J6: =(I6*D6+F6)*G6 -> 361353.22 | K6: Value parsed from "6million"
A7: Rhodes Chest Clinic | B7: GeneXpert machine | C7: Laboratory | D7: 1 | E7: 4000000 | F7: 1000000 | G7: 0.4 | H7: 5 | I7: =IFERROR(E7*0.03/(1-POWER(1.03,-H7)),0) -> 873418.29 | J7: =(I7*D7+F7)*G7 -> 749367.31 | K7: Value "4million", maintenance "1million" parsed
A8: Riruta Health Centre | B8: Spirometer | C8: Spirometry | D8: 1 | E8: 375310 | F8: 0 | G8: 0.74 | H8: 5 | I8: =IFERROR(E8*0.03/(1-POWER(1.03,-H8)),0) -> 81950.654 | J8: =(I8*D8+F8)*G8 -> 60643.484 | K8: Replacement value and maintenance "N/a" -> 0: SPIROMETER COST MISSING, total understated
A9: Riruta Health Centre | B9: Calibration syringe | C9: Spirometry | D9: 1 | E9: 37570 | F9: 0 | G9: 0 | H9: 5 | I9: =IFERROR(E9*0.03/(1-POWER(1.03,-H9)),0) -> 8203.5812 | J9: =(I9*D9+F9)*G9 -> 0 | K9: "N/a" -> 0
A10: Riruta Health Centre | B10: Laptop/tablet for spirometry | C10: Spirometry | D10: 1 | E10: 30000 | F10: 5000 | G10: 1 | H10: 4 | I10: =IFERROR(E10*0.03/(1-POWER(1.03,-H10)),0) -> 8070.8114 | J10: =(I10*D10+F10)*G10 -> 13070.811 | K10: CRD use entered as 1 -> interpreted 100%, could mean 1%
A11: Riruta Health Centre | B11: Pulse oximeter | C11: Triage | D11: 1 | E11: 12000 | F11: 0 | G11: 1 | H11: 3 | I11: =IFERROR(E11*0.03/(1-POWER(1.03,-H11)),0) -> 4242.3644 | J11: =(I11*D11+F11)*G11 -> 4242.3644 | K11: CRD use entered as 100
A12: Riruta Health Centre | B12: Chest X-ray machine | C12: Radiology | D12: 0 | E12: 0 | F12: 0 | G12: 0 | H12: 10 | I12: =IFERROR(E12*0.03/(1-POWER(1.03,-H12)),0) -> 0 | J12: =(I12*D12+F12)*G12 -> 0 | K12: Facility reports no radiology service and 0 X-rays but lists this machine - verify
A13: Riruta Health Centre | B13: GeneXpert machine | C13: Laboratory | D13: 1 | E13: 2000000 | F13: 400000 | G13: 0.6 | H13: 5 | I13: =IFERROR(E13*0.03/(1-POWER(1.03,-H13)),0) -> 436709.14 | J13: =(I13*D13+F13)*G13 -> 502025.49
A14: Karen Health Centre | B14: Spirometer | C14: Spirometry | D14: 0 | E14: 0 | F14: 0 | G14: 0 | H14: 5 | I14: =IFERROR(E14*0.03/(1-POWER(1.03,-H14)),0) -> 0 | J14: =(I14*D14+F14)*G14 -> 0 | K14: Replacement value 5,000 KES implausibly low for a spirometer; CRD use entered as 1 -> interpreted 100%
A15: Karen Health Centre | B15: Calibration syringe | C15: Spirometry | D15: 0 | E15: 0 | F15: 0 | G15: 0 | H15: 5 | I15: =IFERROR(E15*0.03/(1-POWER(1.03,-H15)),0) -> 0 | J15: =(I15*D15+F15)*G15 -> 0 | K15: Quantity raw value 30000 = paste error -> set to 1; CRD use entered as 1 -> 100%
A16: Karen Health Centre | B16: Laptop/tablet for spirometry | C16: Spirometry | D16: 1 | E16: 50000 | F16: 10000 | G16: 0.8 | H16: 4 | I16: =IFERROR(E16*0.03/(1-POWER(1.03,-H16)),0) -> 13451.352 | J16: =(I16*D16+F16)*G16 -> 18761.082
A17: Karen Health Centre | B17: Pulse oximeter | C17: Triage | D17: 1 | E17: 3000 | F17: 1000 | G17: 0.8 | H17: 3 | I17: =IFERROR(E17*0.03/(1-POWER(1.03,-H17)),0) -> 1060.5911 | J17: =(I17*D17+F17)*G17 -> 1648.4729
A18: Karen Health Centre | B18: Chest X-ray machine | C18: Radiology | D18: 0 | E18: 0 | F18: 0 | G18: 0 | H18: 10 | I18: =IFERROR(E18*0.03/(1-POWER(1.03,-H18)),0) -> 0 | J18: =(I18*D18+F18)*G18 -> 0 | K18: Form says radiology not carried out yet reports 205 X-rays and this machine - verify
A19: Karen Health Centre | B19: GeneXpert machine | C19: Laboratory | D19: 0 | E19: 0 | F19: 0 | G19: 0 | H19: 5 | I19: =IFERROR(E19*0.03/(1-POWER(1.03,-H19)),0) -> 0 | J19: =(I19*D19+F19)*G19 -> 0 | K19: Not owned

Sheet Consumables
A1: FacilityName | B1: Item | C1: UnitPriceKES | D1: QtyPerPatient | E1: WastageFactor | F1: VolumeDriver | G1: AnnualVolume | H1: AnnualCostKES | I1: Flag
A2: Rhodes Chest Clinic | B2: Disposable mouthpiece/filter | C2: 500 | D2: 1 | E2: 1.05 | F2: Spirometry | G2: 1500 | H2: =C2*D2*E2*G2 -> 787500 | I2: Volume = 1500 spirometry tests, 6x the 255 CRD patients - verify
A3: Rhodes Chest Clinic | B3: Nose clip | C3: 50 | D3: 1 | E3: 1.05 | F3: Spirometry | G3: 1500 | H3: =C3*D3*E3*G3 -> 78750
A4: Rhodes Chest Clinic | B4: Salbutamol dose | C4: 500 | D4: 3 | E4: 1.05 | F4: Spirometry | G4: 1500 | H4: =C4*D4*E4*G4 -> 2362500 | I4: 600 KES per DOSE x 3 doses is likely the price of a whole inhaler (~200 doses) - HIGH impact, verify
A5: Rhodes Chest Clinic | B5: Disposable gloves (pair) | C5: 5 | D5: 6 | E5: 1.05 | F5: PPTB | G5: 1054 | H5: =C5*D5*E5*G5 -> 33201 | I5: 500 KES/pair and 6 pairs/patient both unusually high - HIGH impact, verify
A6: Rhodes Chest Clinic | B6: Surgical mask/N95 | C6: 120 | D6: 1 | E6: 1.05 | F6: PPTB | G6: 1054 | H6: =C6*D6*E6*G6 -> 132804
A7: Rhodes Chest Clinic | B7: Sputum specimen container | C7: 50 | D7: 2 | E7: 1.05 | F7: PPTB | G7: 1054 | H7: =C7*D7*E7*G7 -> 110670
A8: Rhodes Chest Clinic | B8: Chest X-ray film/printing | C8: 600 | D8: 1 | E8: 1.05 | F8: CXR | G8: 4000 | H8: =C8*D8*E8*G8 -> 2520000 | I8: CXR volume 4000 exceeds TB screening volume - verify
A9: Rhodes Chest Clinic | B9: Stationery/printing/data | C9: 784.31 | D9: 1 | E9: 1.05 | F9: CRD | G9: 255 | H9: =C9*D9*E9*G9 -> 209999 | I9: Raw entry 200,000 per patient impossible; interpreted as annual total -> 784.31/patient
A10: Riruta Health Centre | B10: Disposable mouthpiece/filter | C10: 500 | D10: 2 | E10: 1.05 | F10: Spirometry | G10: 53 | H10: =C10*D10*E10*G10 -> 55650 | I10: Qty cell held date 2026-01-03 = "1-3" entered -> 2
A11: Riruta Health Centre | B11: Nose clip | C11: 50 | D11: 1 | E11: 1.05 | F11: Spirometry | G11: 53 | H11: =C11*D11*E11*G11 -> 2782.5 | I11: 2,500 KES per nose clip unusually high (often reusable) - verify
A12: Riruta Health Centre | B12: Salbutamol dose | C12: 650 | D12: 1 | E12: 1.05 | F12: Spirometry | G12: 53 | H12: =C12*D12*E12*G12 -> 36172.5 | I12: Doses per patient missing -> 0; salbutamol cost excluded
A13: Riruta Health Centre | B13: Disposable gloves (pair) | C13: 5 | D13: 2 | E13: 1.05 | F13: PPTB | G13: 262 | H13: =C13*D13*E13*G13 -> 2751 | I13: 500 KES/pair unusually high - verify
A14: Riruta Health Centre | B14: Surgical mask/N95 | C14: 100 | D14: 1 | E14: 1.05 | F14: PPTB | G14: 262 | H14: =C14*D14*E14*G14 -> 27510
A15: Riruta Health Centre | B15: Sputum specimen container | C15: 50 | D15: 1 | E15: 1.05 | F15: PPTB | G15: 262 | H15: =C15*D15*E15*G15 -> 13755
A16: Riruta Health Centre | B16: Chest X-ray film/printing | C16: 0 | D16: 1 | E16: 1.05 | F16: CXR | G16: 0 | H16: =C16*D16*E16*G16 -> 0 | I16: No radiology; price blank -> 0
A17: Riruta Health Centre | B17: Stationery/printing/data | C17: 200 | D17: 1 | E17: 1.05 | F17: CRD | G17: 1545 | H17: =C17*D17*E17*G17 -> 324450
A18: Karen Health Centre | B18: Disposable mouthpiece/filter | C18: 500 | D18: 1 | E18: 1.05 | F18: Spirometry | G18: 127 | H18: =C18*D18*E18*G18 -> 66675
A19: Karen Health Centre | B19: Nose clip | C19: 50 | D19: 1 | E19: 1.05 | F19: Spirometry | G19: 127 | H19: =C19*D19*E19*G19 -> 6667.5 | I19: 1,500 KES per nose clip unusually high - verify
A20: Karen Health Centre | B20: Salbutamol dose | C20: 200 | D20: 2 | E20: 1.05 | F20: Spirometry | G20: 127 | H20: =C20*D20*E20*G20 -> 53340
A21: Karen Health Centre | B21: Disposable gloves (pair) | C21: 5 | D21: 2 | E21: 1.05 | F21: PPTB | G21: 408 | H21: =C21*D21*E21*G21 -> 4284
A22: Karen Health Centre | B22: Surgical mask/N95 | C22: 200 | D22: 2 | E22: 1.05 | F22: PPTB | G22: 408 | H22: =C22*D22*E22*G22 -> 171360
A23: Karen Health Centre | B23: Sputum specimen container | C23: 50 | D23: 1 | E23: 1.05 | F23: PPTB | G23: 408 | H23: =C23*D23*E23*G23 -> 21420
A24: Karen Health Centre | B24: Chest X-ray film/printing | C24: 0 | D24: 1 | E24: 1.05 | F24: CXR | G24: 205 | H24: =C24*D24*E24*G24 -> 0
A25: Karen Health Centre | B25: Stationery/printing/data | C25: 1000 | D25: 1 | E25: 1.05 | F25: CRD | G25: 366 | H25: =C25*D25*E25*G25 -> 384300

Sheet Space
A1: FacilityName | B1: Room | C1: FloorM2 | D1: AnnualCostKES | E1: TotalFacilityM2 | F1: AllocatedAnnualCostKES | G1: Flag
A2: Rhodes Chest Clinic | B2: Registration/Records | C2: 100 | D2: 600000 | E2: 10000 | F2: =IFERROR(D2*C2/E2,0) -> 6000 | G2: Parsed from "10by10"; all Rhodes dimensions may be feet not metres
A3: Rhodes Chest Clinic | B3: Triage | C3: 200 | D3: 1200000 | E3: 10000 | F3: =IFERROR(D3*C3/E3,0) -> 24000 | G3: "10 by 10"
A4: Rhodes Chest Clinic | B4: Consultation | C4: 100 | D4: 600000 | E4: 10000 | F4: =IFERROR(D4*C4/E4,0) -> 6000 | G4: "10 by 20"
A5: Rhodes Chest Clinic | B5: Laboratory/Sputum | C5: 2000 | D5: 12000000 | E5: 10000 | F5: =IFERROR(D5*C5/E5,0) -> 2400000 | G5: "50 by 40"
A6: Rhodes Chest Clinic | B6: Radiology/X-ray | C6: 2500 | D6: 15000000 | E6: 10000 | F6: =IFERROR(D6*C6/E6,0) -> 3750000 | G6: "50 by 50"
A7: Rhodes Chest Clinic | B7: Spirometry | C7: 100 | D7: 600000 | E7: 10000 | F7: =IFERROR(D7*C7/E7,0) -> 6000 | G7: "10 by 10"
A8: Riruta Health Centre | B8: Registration/Records | C8: 180 | D8: 240000 | E8: 800 | F8: =IFERROR(D8*C8/E8,0) -> 54000 | G8: All Riruta space costs entered 0 (facility-owned building) - SPACE COST MISSING
A9: Riruta Health Centre | B9: Triage | C9: 100 | D9: 240000 | E9: 800 | F9: =IFERROR(D9*C9/E9,0) -> 30000
A10: Riruta Health Centre | B10: Consultation | C10: 90 | D10: 156000 | E10: 800 | F10: =IFERROR(D10*C10/E10,0) -> 17550
A11: Riruta Health Centre | B11: Laboratory/Sputum | C11: 350 | D11: 480000 | E11: 800 | F11: =IFERROR(D11*C11/E11,0) -> 210000
A12: Riruta Health Centre | B12: Radiology/X-ray | C12: 200 | D12: 240000 | E12: 800 | F12: =IFERROR(D12*C12/E12,0) -> 60000
A13: Riruta Health Centre | B13: Spirometry | C13: 100 | D13: 156000 | E13: 800 | F13: =IFERROR(D13*C13/E13,0) -> 19500
A14: Karen Health Centre | B14: Registration/Records | C14: 90 | D14: 120000 | E14: 800 | F14: =IFERROR(D14*C14/E14,0) -> 13500 | G14: "3 X 3"; facility total imputed 800 m2
A15: Karen Health Centre | B15: Triage | C15: 100 | D15: 120000 | E15: 800 | F15: =IFERROR(D15*C15/E15,0) -> 15000 | G15: Raw m2 value 10000 invalid (paste error) -> imputed 10 m2
A16: Karen Health Centre | B16: Consultation | C16: 120 | D16: 144000 | E16: 800 | F16: =IFERROR(D16*C16/E16,0) -> 21600 | G16: "4X3"
A17: Karen Health Centre | B17: Laboratory/Sputum | C17: 90 | D17: 120000 | E17: 800 | F17: =IFERROR(D17*C17/E17,0) -> 13500 | G17: "3X3"
A18: Karen Health Centre | B18: Radiology/X-ray | C18: 200 | D18: 240000 | E18: 800 | F18: =IFERROR(D18*C18/E18,0) -> 60000 | G18: "5X4"
A19: Karen Health Centre | B19: Spirometry | C19: 90 | D19: 120000 | E19: 800 | F19: =IFERROR(D19*C19/E19,0) -> 13500 | G19: "3X3"

Sheet Overheads
A1: FacilityName | B1: Item | C1: AnnualCostKES | D1: AllocationBasis | E1: AllocationShare | F1: AllocatedAnnualCostKES | G1: Flag
A2: Rhodes Chest Clinic | B2: Electricity | C2: 120000 | D2: Floor space | E2: =IF(D2="Floor space",SUMIFS(Space!$C:$C,Space!$A:$A,$A2)/INDEX(Facility!$Q:$Q,MATCH($A2,Facility!$A:$A,0)),IF(D2="CRD volume",INDEX(Facility!$M:$M,MATCH($A2,Facility!$A:$A,0))/INDEX(Facility!$I:$I,MATCH($A2,Facility!$A:$A,0)),AVERAGEIFS(Staff!$I:$I,Staff!$A:$A,$A2))) -> 0.5 | F2: =C2*E2 -> 60000
A3: Rhodes Chest Clinic | B3: Water | C3: 60000 | D3: Floor space | E3: =IF(D3="Floor space",SUMIFS(Space!$C:$C,Space!$A:$A,$A3)/INDEX(Facility!$Q:$Q,MATCH($A3,Facility!$A:$A,0)),IF(D3="CRD volume",INDEX(Facility!$M:$M,MATCH($A3,Facility!$A:$A,0))/INDEX(Facility!$I:$I,MATCH($A3,Facility!$A:$A,0)),AVERAGEIFS(Staff!$I:$I,Staff!$A:$A,$A3))) -> 0.5 | F3: =C3*E3 -> 30000
A4: Rhodes Chest Clinic | B4: Cleaning | C4: 240000 | D4: Floor space | E4: =IF(D4="Floor space",SUMIFS(Space!$C:$C,Space!$A:$A,$A4)/INDEX(Facility!$Q:$Q,MATCH($A4,Facility!$A:$A,0)),IF(D4="CRD volume",INDEX(Facility!$M:$M,MATCH($A4,Facility!$A:$A,0))/INDEX(Facility!$I:$I,MATCH($A4,Facility!$A:$A,0)),AVERAGEIFS(Staff!$I:$I,Staff!$A:$A,$A4))) -> 0.5 | F4: =C4*E4 -> 120000
A5: Rhodes Chest Clinic | B5: Waste management | C5: 120000 | D5: CRD volume | E5: =IF(D5="Floor space",SUMIFS(Space!$C:$C,Space!$A:$A,$A5)/INDEX(Facility!$Q:$Q,MATCH($A5,Facility!$A:$A,0)),IF(D5="CRD volume",INDEX(Facility!$M:$M,MATCH($A5,Facility!$A:$A,0))/INDEX(Facility!$I:$I,MATCH($A5,Facility!$A:$A,0)),AVERAGEIFS(Staff!$I:$I,Staff!$A:$A,$A5))) -> 0.0425 | F5: =C5*E5 -> 5100
A6: Rhodes Chest Clinic | B6: Security | C6: 400000 | D6: Floor space | E6: =IF(D6="Floor space",SUMIFS(Space!$C:$C,Space!$A:$A,$A6)/INDEX(Facility!$Q:$Q,MATCH($A6,Facility!$A:$A,0)),IF(D6="CRD volume",INDEX(Facility!$M:$M,MATCH($A6,Facility!$A:$A,0))/INDEX(Facility!$I:$I,MATCH($A6,Facility!$A:$A,0)),AVERAGEIFS(Staff!$I:$I,Staff!$A:$A,$A6))) -> 0.5 | F6: =C6*E6 -> 200000
A7: Rhodes Chest Clinic | B7: Administration | C7: 400000 | D7: Staff time | E7: =IF(D7="Floor space",SUMIFS(Space!$C:$C,Space!$A:$A,$A7)/INDEX(Facility!$Q:$Q,MATCH($A7,Facility!$A:$A,0)),IF(D7="CRD volume",INDEX(Facility!$M:$M,MATCH($A7,Facility!$A:$A,0))/INDEX(Facility!$I:$I,MATCH($A7,Facility!$A:$A,0)),AVERAGEIFS(Staff!$I:$I,Staff!$A:$A,$A7))) -> 0.28571429 | F7: =C7*E7 -> 114285.71
A8: Rhodes Chest Clinic | B8: ICT/Internet | C8: 120000 | D8: CRD volume | E8: =IF(D8="Floor space",SUMIFS(Space!$C:$C,Space!$A:$A,$A8)/INDEX(Facility!$Q:$Q,MATCH($A8,Facility!$A:$A,0)),IF(D8="CRD volume",INDEX(Facility!$M:$M,MATCH($A8,Facility!$A:$A,0))/INDEX(Facility!$I:$I,MATCH($A8,Facility!$A:$A,0)),AVERAGEIFS(Staff!$I:$I,Staff!$A:$A,$A8))) -> 0.0425 | F8: =C8*E8 -> 5100
A9: Riruta Health Centre | B9: Electricity | C9: 540000 | D9: Floor space | E9: =IF(D9="Floor space",SUMIFS(Space!$C:$C,Space!$A:$A,$A9)/INDEX(Facility!$Q:$Q,MATCH($A9,Facility!$A:$A,0)),IF(D9="CRD volume",INDEX(Facility!$M:$M,MATCH($A9,Facility!$A:$A,0))/INDEX(Facility!$I:$I,MATCH($A9,Facility!$A:$A,0)),AVERAGEIFS(Staff!$I:$I,Staff!$A:$A,$A9))) -> 1.275 | F9: =C9*E9 -> 688500
A10: Riruta Health Centre | B10: Water | C10: 0 | D10: Floor space | E10: =IF(D10="Floor space",SUMIFS(Space!$C:$C,Space!$A:$A,$A10)/INDEX(Facility!$Q:$Q,MATCH($A10,Facility!$A:$A,0)),IF(D10="CRD volume",INDEX(Facility!$M:$M,MATCH($A10,Facility!$A:$A,0))/INDEX(Facility!$I:$I,MATCH($A10,Facility!$A:$A,0)),AVERAGEIFS(Staff!$I:$I,Staff!$A:$A,$A10))) -> 1.275 | F10: =C10*E10 -> 0 | G10: Raw "Borewhole on site" -> 0
A11: Riruta Health Centre | B11: Cleaning | C11: 1800000 | D11: Floor space | E11: =IF(D11="Floor space",SUMIFS(Space!$C:$C,Space!$A:$A,$A11)/INDEX(Facility!$Q:$Q,MATCH($A11,Facility!$A:$A,0)),IF(D11="CRD volume",INDEX(Facility!$M:$M,MATCH($A11,Facility!$A:$A,0))/INDEX(Facility!$I:$I,MATCH($A11,Facility!$A:$A,0)),AVERAGEIFS(Staff!$I:$I,Staff!$A:$A,$A11))) -> 1.275 | F11: =C11*E11 -> 2295000
A12: Riruta Health Centre | B12: Waste management | C12: 300000 | D12: CRD volume | E12: =IF(D12="Floor space",SUMIFS(Space!$C:$C,Space!$A:$A,$A12)/INDEX(Facility!$Q:$Q,MATCH($A12,Facility!$A:$A,0)),IF(D12="CRD volume",INDEX(Facility!$M:$M,MATCH($A12,Facility!$A:$A,0))/INDEX(Facility!$I:$I,MATCH($A12,Facility!$A:$A,0)),AVERAGEIFS(Staff!$I:$I,Staff!$A:$A,$A12))) -> 0.013838953 | F12: =C12*E12 -> 4151.6858 | G12: Parsed from "3,00,000" -> 300,000
A13: Riruta Health Centre | B13: Security | C13: 2400000 | D13: Floor space | E13: =IF(D13="Floor space",SUMIFS(Space!$C:$C,Space!$A:$A,$A13)/INDEX(Facility!$Q:$Q,MATCH($A13,Facility!$A:$A,0)),IF(D13="CRD volume",INDEX(Facility!$M:$M,MATCH($A13,Facility!$A:$A,0))/INDEX(Facility!$I:$I,MATCH($A13,Facility!$A:$A,0)),AVERAGEIFS(Staff!$I:$I,Staff!$A:$A,$A13))) -> 1.275 | F13: =C13*E13 -> 3060000
A14: Riruta Health Centre | B14: Administration | C14: 300000 | D14: Staff time | E14: =IF(D14="Floor space",SUMIFS(Space!$C:$C,Space!$A:$A,$A14)/INDEX(Facility!$Q:$Q,MATCH($A14,Facility!$A:$A,0)),IF(D14="CRD volume",INDEX(Facility!$M:$M,MATCH($A14,Facility!$A:$A,0))/INDEX(Facility!$I:$I,MATCH($A14,Facility!$A:$A,0)),AVERAGEIFS(Staff!$I:$I,Staff!$A:$A,$A14))) -> 0.31497143 | F14: =C14*E14 -> 94491.429 | G14: Parsed from "3,00,000" -> 300,000
A15: Riruta Health Centre | B15: ICT/Internet | C15: 400000 | D15: CRD volume | E15: =IF(D15="Floor space",SUMIFS(Space!$C:$C,Space!$A:$A,$A15)/INDEX(Facility!$Q:$Q,MATCH($A15,Facility!$A:$A,0)),IF(D15="CRD volume",INDEX(Facility!$M:$M,MATCH($A15,Facility!$A:$A,0))/INDEX(Facility!$I:$I,MATCH($A15,Facility!$A:$A,0)),AVERAGEIFS(Staff!$I:$I,Staff!$A:$A,$A15))) -> 0.013838953 | F15: =C15*E15 -> 5535.581
A16: Karen Health Centre | B16: Electricity | C16: 300000 | D16: Floor space | E16: =IF(D16="Floor space",SUMIFS(Space!$C:$C,Space!$A:$A,$A16)/INDEX(Facility!$Q:$Q,MATCH($A16,Facility!$A:$A,0)),IF(D16="CRD volume",INDEX(Facility!$M:$M,MATCH($A16,Facility!$A:$A,0))/INDEX(Facility!$I:$I,MATCH($A16,Facility!$A:$A,0)),AVERAGEIFS(Staff!$I:$I,Staff!$A:$A,$A16))) -> 0.8625 | F16: =C16*E16 -> 258750
A17: Karen Health Centre | B17: Water | C17: 500000 | D17: Floor space | E17: =IF(D17="Floor space",SUMIFS(Space!$C:$C,Space!$A:$A,$A17)/INDEX(Facility!$Q:$Q,MATCH($A17,Facility!$A:$A,0)),IF(D17="CRD volume",INDEX(Facility!$M:$M,MATCH($A17,Facility!$A:$A,0))/INDEX(Facility!$I:$I,MATCH($A17,Facility!$A:$A,0)),AVERAGEIFS(Staff!$I:$I,Staff!$A:$A,$A17))) -> 0.8625 | F17: =C17*E17 -> 431250
A18: Karen Health Centre | B18: Cleaning | C18: 300000 | D18: Floor space | E18: =IF(D18="Floor space",SUMIFS(Space!$C:$C,Space!$A:$A,$A18)/INDEX(Facility!$Q:$Q,MATCH($A18,Facility!$A:$A,0)),IF(D18="CRD volume",INDEX(Facility!$M:$M,MATCH($A18,Facility!$A:$A,0))/INDEX(Facility!$I:$I,MATCH($A18,Facility!$A:$A,0)),AVERAGEIFS(Staff!$I:$I,Staff!$A:$A,$A18))) -> 0.8625 | F18: =C18*E18 -> 258750
A19: Karen Health Centre | B19: Waste management | C19: 150000 | D19: CRD volume | E19: =IF(D19="Floor space",SUMIFS(Space!$C:$C,Space!$A:$A,$A19)/INDEX(Facility!$Q:$Q,MATCH($A19,Facility!$A:$A,0)),IF(D19="CRD volume",INDEX(Facility!$M:$M,MATCH($A19,Facility!$A:$A,0))/INDEX(Facility!$I:$I,MATCH($A19,Facility!$A:$A,0)),AVERAGEIFS(Staff!$I:$I,Staff!$A:$A,$A19))) -> 0.03158985 | F19: =C19*E19 -> 4738.4775
A20: Karen Health Centre | B20: Security | C20: 720000 | D20: Floor space | E20: =IF(D20="Floor space",SUMIFS(Space!$C:$C,Space!$A:$A,$A20)/INDEX(Facility!$Q:$Q,MATCH($A20,Facility!$A:$A,0)),IF(D20="CRD volume",INDEX(Facility!$M:$M,MATCH($A20,Facility!$A:$A,0))/INDEX(Facility!$I:$I,MATCH($A20,Facility!$A:$A,0)),AVERAGEIFS(Staff!$I:$I,Staff!$A:$A,$A20))) -> 0.8625 | F20: =C20*E20 -> 621000
A21: Karen Health Centre | B21: Administration | C21: 500000 | D21: Staff time | E21: =IF(D21="Floor space",SUMIFS(Space!$C:$C,Space!$A:$A,$A21)/INDEX(Facility!$Q:$Q,MATCH($A21,Facility!$A:$A,0)),IF(D21="CRD volume",INDEX(Facility!$M:$M,MATCH($A21,Facility!$A:$A,0))/INDEX(Facility!$I:$I,MATCH($A21,Facility!$A:$A,0)),AVERAGEIFS(Staff!$I:$I,Staff!$A:$A,$A21))) -> 0.22857143 | F21: =C21*E21 -> 114285.71
A22: Karen Health Centre | B22: ICT/Internet | C22: 120000 | D22: CRD volume | E22: =IF(D22="Floor space",SUMIFS(Space!$C:$C,Space!$A:$A,$A22)/INDEX(Facility!$Q:$Q,MATCH($A22,Facility!$A:$A,0)),IF(D22="CRD volume",INDEX(Facility!$M:$M,MATCH($A22,Facility!$A:$A,0))/INDEX(Facility!$I:$I,MATCH($A22,Facility!$A:$A,0)),AVERAGEIFS(Staff!$I:$I,Staff!$A:$A,$A22))) -> 0.03158985 | F22: =C22*E22 -> 3790.782

Sheet Training
A1: FacilityName | B1: Activity | C1: FundingSource | D1: Quantity | E1: UnitCostKES | F1: TotalCostKES | G1: UsefulLifeYears | H1: AnnualizedCostKES | I1: Flag
A2: Rhodes Chest Clinic | B2: TB-CRD pathway training | C2: Research Project | D2: 5 | E2: 40000 | F2: =D2*E2 -> 200000 | G2: 1 | H2: =IF(G2>1,F2*0.03/(1-POWER(1.03,-G2)),F2) -> 200000
A3: Rhodes Chest Clinic | B3: Spirometry competency training | C3: National Government | D3: 5 | E3: 40000 | F3: =D3*E3 -> 200000 | G3: 2 | H3: =IF(G3>1,F3*0.03/(1-POWER(1.03,-G3)),F3) -> 104522.17
A4: Rhodes Chest Clinic | B4: Mentorship/supervision (10 visits) | D4: 1 | E4: 0 | F4: =D4*E4 -> 0 | G4: 1 | H4: =IF(G4>1,F4*0.03/(1-POWER(1.03,-G4)),F4) -> 0 | I4: 10 visits reported but total cost 0 - cost missing
A5: Rhodes Chest Clinic | B5: Job aids, SOPs and registers | D5: 1 | E5: 100000 | F5: =D5*E5 -> 100000 | G5: 1 | H5: =IF(G5>1,F5*0.03/(1-POWER(1.03,-G5)),F5) -> 100000
A6: Rhodes Chest Clinic | B6: Equipment installation and calibration | D6: 1 | E6: 1000000 | F6: =D6*E6 -> 1000000 | G6: 3 | H6: =IF(G6>1,F6*0.03/(1-POWER(1.03,-G6)),F6) -> 353530.36
A7: Rhodes Chest Clinic | B7: Data tools/REDCap setup | D7: 1 | E7: 0 | F7: =D7*E7 -> 0 | G7: 1 | H7: =IF(G7>1,F7*0.03/(1-POWER(1.03,-G7)),F7) -> 0
A8: Riruta Health Centre | B8: TB-CRD pathway training | C8: Donor Funding | D8: 2 | E8: 0 | F8: =D8*E8 -> 0 | G8: 1 | H8: =IF(G8>1,F8*0.03/(1-POWER(1.03,-G8)),F8) -> 0 | I8: Cost per person "N/a" -> 0; donor-funded, economic cost MISSING
A9: Riruta Health Centre | B9: Spirometry competency training | C9: Donor Funding | D9: 1 | E9: 0 | F9: =D9*E9 -> 0 | G9: 2 | H9: =IF(G9>1,F9*0.03/(1-POWER(1.03,-G9)),F9) -> 0 | I9: Cost per person "N/a" -> 0; economic cost MISSING
A10: Riruta Health Centre | B10: Mentorship/supervision (2 visits) | D10: 1 | E10: 0 | F10: =D10*E10 -> 0 | G10: 1 | H10: =IF(G10>1,F10*0.03/(1-POWER(1.03,-G10)),F10) -> 0 | I10: Cost blank -> 0
A11: Riruta Health Centre | B11: Job aids, SOPs and registers | D11: 1 | E11: 0 | F11: =D11*E11 -> 0 | G11: 1 | H11: =IF(G11>1,F11*0.03/(1-POWER(1.03,-G11)),F11) -> 0
A12: Riruta Health Centre | B12: Equipment installation and calibration | D12: 1 | E12: 0 | F12: =D12*E12 -> 0 | G12: 3 | H12: =IF(G12>1,F12*0.03/(1-POWER(1.03,-G12)),F12) -> 0
A13: Riruta Health Centre | B13: Data tools/REDCap setup | D13: 1 | E13: 0 | F13: =D13*E13 -> 0 | G13: 1 | H13: =IF(G13>1,F13*0.03/(1-POWER(1.03,-G13)),F13) -> 0
A14: Karen Health Centre | B14: TB-CRD pathway training | C14: Research Project | D14: 1 | E14: 50000 | F14: =D14*E14 -> 50000 | G14: 1 | H14: =IF(G14>1,F14*0.03/(1-POWER(1.03,-G14)),F14) -> 50000
A15: Karen Health Centre | B15: Spirometry competency training | C15: Research Project | D15: 1 | E15: 50000 | F15: =D15*E15 -> 50000 | G15: 2 | H15: =IF(G15>1,F15*0.03/(1-POWER(1.03,-G15)),F15) -> 26130.542
A16: Karen Health Centre | B16: Mentorship/supervision (3 visits) | D16: 1 | E16: 10000 | F16: =D16*E16 -> 10000 | G16: 1 | H16: =IF(G16>1,F16*0.03/(1-POWER(1.03,-G16)),F16) -> 10000
A17: Karen Health Centre | B17: Job aids, SOPs and registers | D17: 1 | E17: 1000 | F17: =D17*E17 -> 1000 | G17: 1 | H17: =IF(G17>1,F17*0.03/(1-POWER(1.03,-G17)),F17) -> 1000
A18: Karen Health Centre | B18: Equipment installation and calibration | D18: 1 | E18: 10000 | F18: =D18*E18 -> 10000 | G18: 3 | H18: =IF(G18>1,F18*0.03/(1-POWER(1.03,-G18)),F18) -> 3535.3036
A19: Karen Health Centre | B19: Data tools/REDCap setup | D19: 1 | E19: 5000 | F19: =D19*E19 -> 5000 | G19: 1 | H19: =IF(G19>1,F19*0.03/(1-POWER(1.03,-G19)),F19) -> 5000

Sheet Observations
A1: FacilityName | B1: Stage | C1: MinutesPerPatient | D1: PatientsObserved | E1: Flag
A2: Rhodes Chest Clinic | B2: Registration/Triage | C2: 10 | D2: 6
A3: Rhodes Chest Clinic | B3: Clinical Consultation | C3: 10 | D3: 7
A4: Rhodes Chest Clinic | B4: TB Screening | C4: 5 | D4: 10
A5: Rhodes Chest Clinic | B5: Laboratory | C5: 10 | D5: 10
A6: Rhodes Chest Clinic | B6: Radiology | C6: 10 | D6: 10
A7: Rhodes Chest Clinic | B7: Spirometry Pre-Test | C7: 20 | D7: 8
A8: Rhodes Chest Clinic | B8: Spirometry Baseline | C8: 30 | D8: 8
A9: Rhodes Chest Clinic | B9: Spirometry Post-Bronchodilator | C9: 30 | D9: 8
A10: Rhodes Chest Clinic | B10: Diagnosis/Review | C10: 20
A11: Rhodes Chest Clinic | B11: Counselling/Referral | C11: 10
A12: Rhodes Chest Clinic | B12: Data Capture | C12: 5
A13: Riruta Health Centre | B13: Registration/Triage | C13: 7.5 | D13: 5 | E13: "5-10mins" -> 7.5
A14: Riruta Health Centre | B14: Clinical Consultation | C14: 30 | D14: 30
A15: Riruta Health Centre | B15: TB Screening | C15: 7.5 | D15: 5 | E15: "5-10mins" -> 7.5
A16: Riruta Health Centre | B16: Laboratory | C16: 270 | D16: 5 | E16: "4-5hours" -> 270 min (likely includes result turnaround, not hands-on time)
A17: Riruta Health Centre | B17: Spirometry Pre-Test | C17: 15 | D17: 8
A18: Riruta Health Centre | B18: Spirometry Baseline | C18: 7.5 | D18: 8 | E18: Cell held date 2026-05-10 = "5-10" entered -> 7.5
A19: Riruta Health Centre | B19: Spirometry Post-Bronchodilator | C19: 10 | D19: 8 | E19: Cell held date 2026-05-15 = "5-15" entered -> 10
A20: Riruta Health Centre | B20: Counselling/Referral | C20: 25 | E20: "20-30" -> 25
A21: Riruta Health Centre | B21: Data Capture | C21: 20 | E21: "15-25" -> 20
A22: Karen Health Centre | B22: Registration/Triage | C22: 15 | D22: 5
A23: Karen Health Centre | B23: Clinical Consultation | C23: 10 | D23: 5
A24: Karen Health Centre | B24: TB Screening | C24: 15 | D24: 5
A25: Karen Health Centre | B25: Laboratory | C25: 20 | D25: 5
A26: Karen Health Centre | B26: Spirometry Pre-Test | C26: 5 | D26: 5
A27: Karen Health Centre | B27: Spirometry Baseline | C27: 10 | D27: 5
A28: Karen Health Centre | B28: Spirometry Post-Bronchodilator | C28: 5 | D28: 5
A29: Karen Health Centre | B29: Diagnosis/Review | C29: 5
A30: Karen Health Centre | B30: Counselling/Referral | C30: 5
A31: Karen Health Centre | B31: Data Capture | C31: 5

Sheet CostSummary
A1: FacilityName | B1: StaffKES | C1: EquipmentKES | D1: ConsumablesKES | E1: SpaceKES | F1: OverheadsKES | G1: TrainingKES | H1: TotalAnnualCRDCostKES | I1: AnnualCRDPatients | J1: AnnualPPTB_Eligible | K1: AnnualTBScreened | L1: CostPerCRDPatientKES | M1: CostPerPPTBEligibleKES | N1: CostPerPresumptiveTBKES
A2: Rhodes Chest Clinic | B2: =SUMIFS(Staff!$J:$J,Staff!$A:$A,$A2) -> 2121600 | C2: =SUMIFS(Equipment!$J:$J,Equipment!$A:$A,$A2) -> 1228097.9 | D2: =SUMIFS(Consumables!$H:$H,Consumables!$A:$A,$A2) -> 6235424 | E2: =SUMIFS(Space!$F:$F,Space!$A:$A,$A2) -> 6192000 | F2: =SUMIFS(Overheads!$F:$F,Overheads!$A:$A,$A2) -> 534485.71 | G2: =SUMIFS(Training!$H:$H,Training!$A:$A,$A2) -> 758052.53 | H2: =SUM(B2:G2) -> 17069660 | I2: =INDEX(Facility!$M:$M,MATCH($A2,Facility!$A:$A,0)) -> 255 | J2: =INDEX(Facility!$L:$L,MATCH($A2,Facility!$A:$A,0)) -> 929 | K2: =INDEX(Facility!$J:$J,MATCH($A2,Facility!$A:$A,0)) -> 3671 | L2: =IFERROR(H2/I2,0) -> 66939.844 | M2: =IFERROR(H2/J2,0) -> 18374.23 | N2: =IFERROR(H2/K2,0) -> 4649.8665
A3: Riruta Health Centre | B3: =SUMIFS(Staff!$J:$J,Staff!$A:$A,$A3) -> 1363680 | C3: =SUMIFS(Equipment!$J:$J,Equipment!$A:$A,$A3) -> 579982.15 | D3: =SUMIFS(Consumables!$H:$H,Consumables!$A:$A,$A3) -> 463071 | E3: =SUMIFS(Space!$F:$F,Space!$A:$A,$A3) -> 391050 | F3: =SUMIFS(Overheads!$F:$F,Overheads!$A:$A,$A3) -> 6147678.7 | G3: =SUMIFS(Training!$H:$H,Training!$A:$A,$A3) -> 0 | H3: =SUM(B3:G3) -> 8945461.8 | I3: =INDEX(Facility!$M:$M,MATCH($A3,Facility!$A:$A,0)) -> 204 | J3: =INDEX(Facility!$L:$L,MATCH($A3,Facility!$A:$A,0)) -> 1256 | K3: =INDEX(Facility!$J:$J,MATCH($A3,Facility!$A:$A,0)) -> 11930 | L3: =IFERROR(H3/I3,0) -> 43850.303 | M3: =IFERROR(H3/J3,0) -> 7122.183 | N3: =IFERROR(H3/K3,0) -> 749.82916
A4: Karen Health Centre | B4: =SUMIFS(Staff!$J:$J,Staff!$A:$A,$A4) -> 2007000 | C4: =SUMIFS(Equipment!$J:$J,Equipment!$A:$A,$A4) -> 20409.555 | D4: =SUMIFS(Consumables!$H:$H,Consumables!$A:$A,$A4) -> 708046.5 | E4: =SUMIFS(Space!$F:$F,Space!$A:$A,$A4) -> 137100 | F4: =SUMIFS(Overheads!$F:$F,Overheads!$A:$A,$A4) -> 1692565 | G4: =SUMIFS(Training!$H:$H,Training!$A:$A,$A4) -> 95665.846 | H4: =SUM(B4:G4) -> 4660786.9 | I4: =INDEX(Facility!$M:$M,MATCH($A4,Facility!$A:$A,0)) -> 366 | J4: =INDEX(Facility!$L:$L,MATCH($A4,Facility!$A:$A,0)) -> 408 | K4: =INDEX(Facility!$J:$J,MATCH($A4,Facility!$A:$A,0)) -> 752 | L4: =IFERROR(H4/I4,0) -> 12734.39 | M4: =IFERROR(H4/J4,0) -> 11423.497 | N4: =IFERROR(H4/K4,0) -> 6197.8549
A5: ALL FACILITIES | B5: =SUM(B2:B4) -> 5492280 | C5: =SUM(C2:C4) -> 1828489.6 | D5: =SUM(D2:D4) -> 7406541.5 | E5: =SUM(E2:E4) -> 6720150 | F5: =SUM(F2:F4) -> 8374729.4 | G5: =SUM(G2:G4) -> 853718.38 | H5: =SUM(H2:H4) -> 30675909 | I5: =SUM(I2:I4) -> 825 | ... K5: =SUM(K2:K4) -> 16353 | L5: =IFERROR(H5/I5,0) -> 37182.92 | M5: =IFERROR(H5/J5,0) -> 11830.277 | N5: =IFERROR(H5/K5,0) -> 1875.8582
